tools/__init__.py
tools/base.py
tools/core.py
tools/commands/__init__.py
tools/commands/convert.py
tools/commands/encrypt.py
xinlan_tools-0.0.2.dist-info/LICENSE
xinlan_tools-0.0.2.dist-info/METADATA
xinlan_tools-0.0.2.dist-info/WHEEL
xinlan_tools-0.0.2.dist-info/entry_points.txt
xinlan_tools-0.0.2.dist-info/top_level.txt
xinlan_tools-0.0.2.dist-info/RECORD
